artd_partner/__init__.py
artd_partner/admin.py
artd_partner/apps.py
artd_partner/models.py
artd_partner/signals.py
artd_partner/data/__init__.py
artd_partner/data/languages.py
artd_partner/locale/en/LC_MESSAGES/django.po
artd_partner/locale/es/LC_MESSAGES/django.po
artd_partner/management/__init__.py
artd_partner/management/commands/__init__.py
artd_partner/management/commands/populate_user_in_coworker.py
artd_partner/migrations/0001_initial.py
artd_partner/migrations/0002_alter_coworker_dni_alter_coworker_first_name_and_more.py
artd_partner/migrations/0003_alter_coworker_created_at_alter_coworker_status_and_more.py
artd_partner/migrations/0004_alter_coworker_created_at_alter_coworker_updated_at_and_more.py
artd_partner/migrations/0005_alter_coworker_created_at_alter_coworker_updated_at_and_more.py
artd_partner/migrations/0006_partner_services.py
artd_partner/migrations/0007_position_partner.py
artd_partner/migrations/0008_partner_document_type.py
artd_partner/migrations/0009_alter_partner_document_type.py
artd_partner/migrations/0010_partner_signed_key.py
artd_partner/migrations/0011_coworker_created_by.py
artd_partner/migrations/0012_rename_created_by_coworker_user.py
artd_partner/migrations/0013_alter_coworker_headquarter_alter_coworker_position_and_more.py
artd_partner/migrations/__init__.py
artd_partner/utils/__init__.py
artd_partner/utils/generators.py
partner/__init__.py
partner/asgi.py
partner/settings.py
partner/urls.py
partner/wsgi.py
artd_partner-1.0.14.dist-info/LICENSE
artd_partner-1.0.14.dist-info/METADATA
artd_partner-1.0.14.dist-info/WHEEL
artd_partner-1.0.14.dist-info/top_level.txt
artd_partner-1.0.14.dist-info/RECORD
